LICENSE
MANIFEST.in
README.md
setup.py
inmatelocator/__init__.py
inmatelocator/utils.py
inmatelocator.egg-info/PKG-INFO
inmatelocator.egg-info/SOURCES.txt
inmatelocator.egg-info/dependency_links.txt
inmatelocator.egg-info/requires.txt
inmatelocator.egg-info/top_level.txt
inmatelocator/data/federal.json
inmatelocator/data/florida.json
inmatelocator/data/texas.json
inmatelocator/stateparsers/__init__.py
inmatelocator/stateparsers/california.py
inmatelocator/stateparsers/federal.py
inmatelocator/stateparsers/florida.py
inmatelocator/stateparsers/newyork.py
inmatelocator/stateparsers/texas.py