Metadata-Version: 1.0
Name: inmatelocator
Version: 0.0.8
Summary: Library for locating people incarcerated in the US by querying official prison search tools
Home-page: https://bitbucket.org/yourcelf/inmatelocator
Author: Charlie DeTar
Author-email: cfd@media.mit.edu
License: MPL
Platform: UNKNOWN
